{
    "s2PR4.0_2(1)u": {
        "Poniedziałek 2026-02-16": [
            {
                "time": "08:15-09:45",
                "class_name": "Praktyki (zp)",
                "short_name": "Prakt (zp)",
                "teacher": "PRAKTYKI",
                "room": "Praktyki1"
            },
            {
                "time": "10:00-11:30",
                "class_name": "Praktyki (zp)",
                "short_name": "Prakt (zp)",
                "teacher": "PRAKTYKI",
                "room": "Praktyki1"
            },
            {
                "time": "11:45-13:15",
                "class_name": "Praktyki (zp)",
                "short_name": "Prakt (zp)",
                "teacher": "PRAKTYKI",
                "room": "Praktyki1"
            },
            {
                "time": "13:30-15:00",
                "class_name": "Praktyki (zp)",
                "short_name": "Prakt (zp)",
                "teacher": "PRAKTYKI",
                "room": "Praktyki1"
            }
        ],
        "Wtorek 2026-02-17": [
            {
                "time": "08:15-09:45",
                "class_name": "Praktyki (zp)",
                "short_name": "Prakt (zp)",
                "teacher": "PRAKTYKI",
                "room": "Praktyki1"
            },
            {
                "time": "10:00-11:30",
                "class_name": "Praktyki (zp)",
                "short_name": "Prakt (zp)",
                "teacher": "PRAKTYKI",
                "room": "Praktyki1"
            },
            {
                "time": "11:45-13:15",
                "class_name": "Praktyki (zp)",
                "short_name": "Prakt (zp)",
                "teacher": "PRAKTYKI",
                "room": "Praktyki1"
            },
            {
                "time": "13:30-15:00",
                "class_name": "Praktyki (zp)",
                "short_name": "Prakt (zp)",
                "teacher": "PRAKTYKI",
                "room": "Praktyki1"
            }
        ],
        "Środa 2026-02-18": [
            {
                "time": "08:15-09:45",
                "class_name": "Praktyki (zp)",
                "short_name": "Prakt (zp)",
                "teacher": "PRAKTYKI",
                "room": "Praktyki1"
            },
            {
                "time": "10:00-11:30",
                "class_name": "Praktyki (zp)",
                "short_name": "Prakt (zp)",
                "teacher": "PRAKTYKI",
                "room": "Praktyki1"
            },
            {
                "time": "11:45-13:15",
                "class_name": "Praktyki (zp)",
                "short_name": "Prakt (zp)",
                "teacher": "PRAKTYKI",
                "room": "Praktyki1"
            },
            {
                "time": "13:30-15:00",
                "class_name": "Praktyki (zp)",
                "short_name": "Prakt (zp)",
                "teacher": "PRAKTYKI",
                "room": "Praktyki1"
            }
        ],
        "Czwartek 2026-02-19": [
            {
                "time": "08:15-09:45",
                "class_name": "Praktyki (zp)",
                "short_name": "Prakt (zp)",
                "teacher": "PRAKTYKI",
                "room": "Praktyki1"
            },
            {
                "time": "10:00-11:30",
                "class_name": "Praktyki (zp)",
                "short_name": "Prakt (zp)",
                "teacher": "PRAKTYKI",
                "room": "Praktyki1"
            },
            {
                "time": "11:45-13:15",
                "class_name": "Praktyki (zp)",
                "short_name": "Prakt (zp)",
                "teacher": "PRAKTYKI",
                "room": "Praktyki1"
            },
            {
                "time": "13:30-15:00",
                "class_name": "Praktyki (zp)",
                "short_name": "Prakt (zp)",
                "teacher": "PRAKTYKI",
                "room": "Praktyki1"
            },
            {
                "time": "17:00-18:30",
                "class_name": "Zintegrowane systemy informatyczne zarządzania (wyk)",
                "short_name": "Zsiz (wyk)",
                "teacher": "mgr inż. Dawid Kucuk",
                "room": "C224"
            }
        ],
        "Piątek 2026-02-20": [
            {
                "time": "08:15-09:45",
                "class_name": "Praktyki (zp)",
                "short_name": "Prakt (zp)",
                "teacher": "PRAKTYKI",
                "room": "Praktyki1"
            },
            {
                "time": "10:00-11:30",
                "class_name": "Praktyki (zp)",
                "short_name": "Prakt (zp)",
                "teacher": "PRAKTYKI",
                "room": "Praktyki1"
            },
            {
                "time": "11:45-13:15",
                "class_name": "Praktyki (zp)",
                "short_name": "Prakt (zp)",
                "teacher": "PRAKTYKI",
                "room": "Praktyki1"
            },
            {
                "time": "13:30-15:00",
                "class_name": "Praktyki (zp)",
                "short_name": "Prakt (zp)",
                "teacher": "PRAKTYKI",
                "room": "Praktyki1"
            },
            {
                "time": "17:00-18:30",
                "class_name": "Seminarium dyplomowe (sem)",
                "short_name": "Sd (sem)",
                "teacher": "prof. dr hab. inż. Anna Burduk / dr inż. Rafał Więcławek",
                "room": "C202 / C209"
            },
            {
                "time": "18:45-20:15",
                "class_name": "Eksploatacja maszyn i urządzeń (wyk)",
                "short_name": "Emiu (wyk)",
                "teacher": "dr inż. Zygmunt Domagała",
                "room": "C125"
            }
        ],
        "Poniedziałek 2026-02-23": [
            {
                "time": "08:15-09:45",
                "class_name": "Praktyki (zp)",
                "short_name": "Prakt (zp)",
                "teacher": "PRAKTYKI",
                "room": "Praktyki1"
            },
            {
                "time": "10:00-11:30",
                "class_name": "Praktyki (zp)",
                "short_name": "Prakt (zp)",
                "teacher": "PRAKTYKI",
                "room": "Praktyki1"
            },
            {
                "time": "11:45-13:15",
                "class_name": "Praktyki (zp)",
                "short_name": "Prakt (zp)",
                "teacher": "PRAKTYKI",
                "room": "Praktyki1"
            },
            {
                "time": "13:30-15:00",
                "class_name": "Praktyki (zp)",
                "short_name": "Prakt (zp)",
                "teacher": "PRAKTYKI",
                "room": "Praktyki1"
            }
        ],
        "Wtorek 2026-02-24": [
            {
                "time": "08:15-09:45",
                "class_name": "Praktyki (zp)",
                "short_name": "Prakt (zp)",
                "teacher": "PRAKTYKI",
                "room": "Praktyki1"
            },
            {
                "time": "10:00-11:30",
                "class_name": "Praktyki (zp)",
                "short_name": "Prakt (zp)",
                "teacher": "PRAKTYKI",
                "room": "Praktyki1"
            },
            {
                "time": "11:45-13:15",
                "class_name": "Praktyki (zp)",
                "short_name": "Prakt (zp)",
                "teacher": "PRAKTYKI",
                "room": "Praktyki1"
            },
            {
                "time": "13:30-15:00",
                "class_name": "Praktyki (zp)",
                "short_name": "Prakt (zp)",
                "teacher": "PRAKTYKI",
                "room": "Praktyki1"
            }
        ],
        "Środa 2026-02-25": [
            {
                "time": "08:15-09:45",
                "class_name": "Praktyki (zp)",
                "short_name": "Prakt (zp)",
                "teacher": "PRAKTYKI",
                "room": "Praktyki1"
            },
            {
                "time": "10:00-11:30",
                "class_name": "Praktyki (zp)",
                "short_name": "Prakt (zp)",
                "teacher": "PRAKTYKI",
                "room": "Praktyki1"
            },
            {
                "time": "11:45-13:15",
                "class_name": "Praktyki (zp)",
                "short_name": "Prakt (zp)",
                "teacher": "PRAKTYKI",
                "room": "Praktyki1"
            },
            {
                "time": "13:30-15:00",
                "class_name": "Praktyki (zp)",
                "short_name": "Prakt (zp)",
                "teacher": "PRAKTYKI",
                "room": "Praktyki1"
            }
        ],
        "Czwartek 2026-02-26": [
            {
                "time": "08:15-09:45",
                "class_name": "Praktyki (zp)",
                "short_name": "Prakt (zp)",
                "teacher": "PRAKTYKI",
                "room": "Praktyki1"
            },
            {
                "time": "10:00-11:30",
                "class_name": "Praktyki (zp)",
                "short_name": "Prakt (zp)",
                "teacher": "PRAKTYKI",
                "room": "Praktyki1"
            },
            {
                "time": "11:45-13:15",
                "class_name": "Praktyki (zp)",
                "short_name": "Prakt (zp)",
                "teacher": "PRAKTYKI",
                "room": "Praktyki1"
            },
            {
                "time": "13:30-15:00",
                "class_name": "Praktyki (zp)",
                "short_name": "Prakt (zp)",
                "teacher": "PRAKTYKI",
                "room": "Praktyki1"
            },
            {
                "time": "17:00-18:30",
                "class_name": "Zintegrowane systemy informatyczne zarządzania (wyk)",
                "short_name": "Zsiz (wyk)",
                "teacher": "mgr inż. Dawid Kucuk",
                "room": "Online_03"
            }
        ],
        "Piątek 2026-02-27": [
            {
                "time": "08:15-09:45",
                "class_name": "Praktyki (zp)",
                "short_name": "Prakt (zp)",
                "teacher": "PRAKTYKI",
                "room": "Praktyki1"
            },
            {
                "time": "10:00-11:30",
                "class_name": "Praktyki (zp)",
                "short_name": "Prakt (zp)",
                "teacher": "PRAKTYKI",
                "room": "Praktyki1"
            },
            {
                "time": "11:45-13:15",
                "class_name": "Praktyki (zp)",
                "short_name": "Prakt (zp)",
                "teacher": "PRAKTYKI",
                "room": "Praktyki1"
            },
            {
                "time": "13:30-15:00",
                "class_name": "Praktyki (zp)",
                "short_name": "Prakt (zp)",
                "teacher": "PRAKTYKI",
                "room": "Praktyki1"
            },
            {
                "time": "17:00-18:30",
                "class_name": "Seminarium dyplomowe (sem)",
                "short_name": "Sd (sem)",
                "teacher": "prof. dr hab. inż. Anna Burduk / dr inż. Rafał Więcławek",
                "room": "Online_08 / Online_10"
            },
            {
                "time": "18:45-20:15",
                "class_name": "Eksploatacja maszyn i urządzeń (wyk)",
                "short_name": "Emiu (wyk)",
                "teacher": "dr inż. Zygmunt Domagała",
                "room": "Online_07"
            }
        ],
        "Sobota 2026-02-28": [
            {
                "time": "08:15-09:45",
                "class_name": "Rola współczesnego menedżera w przemyśle 4.0 (wt)",
                "short_name": "Rwmwp4 (wt)",
                "teacher": "mgr inż. Piotr Motyka",
                "room": "A16"
            },
            {
                "time": "10:00-11:30",
                "class_name": "Eksploatacja maszyn i urządzeń (wt)",
                "short_name": "Emiu (wt)",
                "teacher": "dr inż. Zygmunt Domagała",
                "room": "C202"
            },
            {
                "time": "11:45-13:15",
                "class_name": "Coboty w przemyśle (lab)",
                "short_name": "Cwp (lab)",
                "teacher": "mgr inż. Jakub Wisłocki",
                "room": "D6"
            },
            {
                "time": "13:45-15:15",
                "class_name": "Coboty w przemyśle (lab)",
                "short_name": "Cwp (lab)",
                "teacher": "mgr inż. Jakub Wisłocki",
                "room": "D6"
            },
            {
                "time": "15:30-17:00",
                "class_name": "Seminarium dyplomowe (sem)",
                "short_name": "Sd (sem)",
                "teacher": "prof. dr hab. inż. Robert Burduk",
                "room": "C209"
            },
            {
                "time": "17:15-18:45",
                "class_name": "Zintegrowane systemy informatyczne zarządzania (lab)",
                "short_name": "Zsiz (lab)",
                "teacher": "mgr inż. Dawid Kucuk",
                "room": "C314"
            },
            {
                "time": "19:00-20:30",
                "class_name": "Rola współczesnego menedżera w przemyśle 4.0 (wt)",
                "short_name": "Rwmwp4 (wt)",
                "teacher": "mgr inż. Piotr Motyka",
                "room": "C202"
            }
        ],
        "Niedziela 2026-03-01": [
            {
                "time": "08:15-09:45",
                "class_name": "Zintegrowane systemy informatyczne zarządzania (lab)",
                "short_name": "Zsiz (lab)",
                "teacher": "mgr inż. Dawid Kucuk",
                "room": "A242"
            },
            {
                "time": "10:00-11:30",
                "class_name": "Coboty w przemyśle (lab)",
                "short_name": "Cwp (lab)",
                "teacher": "mgr inż. Jakub Wisłocki",
                "room": "D6"
            },
            {
                "time": "11:45-13:15",
                "class_name": "Rola współczesnego menedżera w przemyśle 4.0 (wt)",
                "short_name": "Rwmwp4 (wt)",
                "teacher": "mgr inż. Piotr Motyka",
                "room": "C202"
            },
            {
                "time": "13:45-15:15",
                "class_name": "Rola współczesnego menedżera w przemyśle 4.0 (wt)",
                "short_name": "Rwmwp4 (wt)",
                "teacher": "mgr inż. Piotr Motyka",
                "room": "C202"
            },
            {
                "time": "15:30-17:00",
                "class_name": "Eksploatacja maszyn i urządzeń (wt)",
                "short_name": "Emiu (wt)",
                "teacher": "dr inż. Zygmunt Domagała",
                "room": "C203"
            },
            {
                "time": "17:15-18:45",
                "class_name": "Eksploatacja maszyn i urządzeń (wt)",
                "short_name": "Emiu (wt)",
                "teacher": "dr inż. Zygmunt Domagała",
                "room": "C203"
            },
            {
                "time": "19:00-20:30",
                "class_name": "Coboty w przemyśle (lab)",
                "short_name": "Cwp (lab)",
                "teacher": "mgr inż. Jakub Wisłocki",
                "room": "D6"
            }
        ],
        "Poniedziałek 2026-03-02": [
            {
                "time": "08:15-09:45",
                "class_name": "Praktyki (zp)",
                "short_name": "Prakt (zp)",
                "teacher": "PRAKTYKI",
                "room": "Praktyki1"
            },
            {
                "time": "10:00-11:30",
                "class_name": "Praktyki (zp)",
                "short_name": "Prakt (zp)",
                "teacher": "PRAKTYKI",
                "room": "Praktyki1"
            },
            {
                "time": "11:45-13:15",
                "class_name": "Praktyki (zp)",
                "short_name": "Prakt (zp)",
                "teacher": "PRAKTYKI",
                "room": "Praktyki1"
            },
            {
                "time": "13:30-15:00",
                "class_name": "Praktyki (zp)",
                "short_name": "Prakt (zp)",
                "teacher": "PRAKTYKI",
                "room": "Praktyki1"
            }
        ],
        "Wtorek 2026-03-03": [
            {
                "time": "08:15-09:45",
                "class_name": "Praktyki (zp)",
                "short_name": "Prakt (zp)",
                "teacher": "PRAKTYKI",
                "room": "Praktyki1"
            },
            {
                "time": "10:00-11:30",
                "class_name": "Praktyki (zp)",
                "short_name": "Prakt (zp)",
                "teacher": "PRAKTYKI",
                "room": "Praktyki1"
            },
            {
                "time": "11:45-13:15",
                "class_name": "Praktyki (zp)",
                "short_name": "Prakt (zp)",
                "teacher": "PRAKTYKI",
                "room": "Praktyki1"
            },
            {
                "time": "13:30-15:00",
                "class_name": "Praktyki (zp)",
                "short_name": "Prakt (zp)",
                "teacher": "PRAKTYKI",
                "room": "Praktyki1"
            },
            {
                "time": "18:45-20:15",
                "class_name": "Seminarium dyplomowe (sem)",
                "short_name": "Sd (sem)",
                "teacher": "prof. dr hab. inż. Robert Burduk",
                "room": "Online_104"
            }
        ],
        "Środa 2026-03-04": [
            {
                "time": "08:15-09:45",
                "class_name": "Praktyki (zp)",
                "short_name": "Prakt (zp)",
                "teacher": "PRAKTYKI",
                "room": "Praktyki1"
            },
            {
                "time": "10:00-11:30",
                "class_name": "Praktyki (zp)",
                "short_name": "Prakt (zp)",
                "teacher": "PRAKTYKI",
                "room": "Praktyki1"
            },
            {
                "time": "11:45-13:15",
                "class_name": "Praktyki (zp)",
                "short_name": "Prakt (zp)",
                "teacher": "PRAKTYKI",
                "room": "Praktyki1"
            },
            {
                "time": "13:30-15:00",
                "class_name": "Praktyki (zp)",
                "short_name": "Prakt (zp)",
                "teacher": "PRAKTYKI",
                "room": "Praktyki1"
            }
        ],
        "Czwartek 2026-03-05": [
            {
                "time": "08:15-09:45",
                "class_name": "Praktyki (zp)",
                "short_name": "Prakt (zp)",
                "teacher": "PRAKTYKI",
                "room": "Praktyki1"
            },
            {
                "time": "10:00-11:30",
                "class_name": "Praktyki (zp)",
                "short_name": "Prakt (zp)",
                "teacher": "PRAKTYKI",
                "room": "Praktyki1"
            },
            {
                "time": "11:45-13:15",
                "class_name": "Praktyki (zp)",
                "short_name": "Prakt (zp)",
                "teacher": "PRAKTYKI",
                "room": "Praktyki1"
            },
            {
                "time": "13:30-15:00",
                "class_name": "Praktyki (zp)",
                "short_name": "Prakt (zp)",
                "teacher": "PRAKTYKI",
                "room": "Praktyki1"
            },
            {
                "time": "18:45-20:15",
                "class_name": "Zintegrowane systemy informatyczne zarządzania (wyk)",
                "short_name": "Zsiz (wyk)",
                "teacher": "mgr inż. Dawid Kucuk",
                "room": "Online_08"
            }
        ],
        "Piątek 2026-03-06": [
            {
                "time": "08:15-09:45",
                "class_name": "Praktyki (zp)",
                "short_name": "Prakt (zp)",
                "teacher": "PRAKTYKI",
                "room": "Praktyki1"
            },
            {
                "time": "10:00-11:30",
                "class_name": "Praktyki (zp)",
                "short_name": "Prakt (zp)",
                "teacher": "PRAKTYKI",
                "room": "Praktyki1"
            },
            {
                "time": "11:45-13:15",
                "class_name": "Praktyki (zp)",
                "short_name": "Prakt (zp)",
                "teacher": "PRAKTYKI",
                "room": "Praktyki1"
            },
            {
                "time": "13:30-15:00",
                "class_name": "Praktyki (zp)",
                "short_name": "Prakt (zp)",
                "teacher": "PRAKTYKI",
                "room": "Praktyki1"
            },
            {
                "time": "17:00-18:30",
                "class_name": "Seminarium dyplomowe (sem)",
                "short_name": "Sd (sem)",
                "teacher": "dr inż. Rafał Więcławek / prof. dr hab. inż. Anna Burduk",
                "room": "Online_08 / Online_09"
            },
            {
                "time": "18:45-20:15",
                "class_name": "Eksploatacja maszyn i urządzeń (wyk)",
                "short_name": "Emiu (wyk)",
                "teacher": "dr inż. Zygmunt Domagała",
                "room": "Online_100"
            }
        ],
        "Niedziela 2026-03-08": [
            {
                "time": "08:15-09:45",
                "class_name": "Rola współczesnego menedżera w przemyśle 4.0 (wt)",
                "short_name": "Rwmwp4 (wt)",
                "teacher": "mgr inż. Piotr Motyka",
                "room": "A217"
            },
            {
                "time": "10:00-11:30",
                "class_name": "Rola współczesnego menedżera w przemyśle 4.0 (wt)",
                "short_name": "Rwmwp4 (wt)",
                "teacher": "mgr inż. Piotr Motyka",
                "room": "A217"
            },
            {
                "time": "11:45-13:15",
                "class_name": "Zintegrowane systemy informatyczne zarządzania (lab)",
                "short_name": "Zsiz (lab)",
                "teacher": "mgr inż. Dawid Kucuk",
                "room": "A244"
            },
            {
                "time": "13:45-15:15",
                "class_name": "Zintegrowane systemy informatyczne zarządzania (lab)",
                "short_name": "Zsiz (lab)",
                "teacher": "mgr inż. Dawid Kucuk",
                "room": "A244"
            }
        ],
        "Poniedziałek 2026-03-09": [
            {
                "time": "08:15-09:45",
                "class_name": "Praktyki (zp)",
                "short_name": "Prakt (zp)",
                "teacher": "PRAKTYKI",
                "room": "Praktyki1"
            },
            {
                "time": "10:00-11:30",
                "class_name": "Praktyki (zp)",
                "short_name": "Prakt (zp)",
                "teacher": "PRAKTYKI",
                "room": "Praktyki1"
            },
            {
                "time": "11:45-13:15",
                "class_name": "Praktyki (zp)",
                "short_name": "Prakt (zp)",
                "teacher": "PRAKTYKI",
                "room": "Praktyki1"
            },
            {
                "time": "13:30-15:00",
                "class_name": "Praktyki (zp)",
                "short_name": "Prakt (zp)",
                "teacher": "PRAKTYKI",
                "room": "Praktyki1"
            }
        ],
        "Wtorek 2026-03-10": [
            {
                "time": "08:15-09:45",
                "class_name": "Praktyki (zp)",
                "short_name": "Prakt (zp)",
                "teacher": "PRAKTYKI",
                "room": "Praktyki1"
            },
            {
                "time": "10:00-11:30",
                "class_name": "Praktyki (zp)",
                "short_name": "Prakt (zp)",
                "teacher": "PRAKTYKI",
                "room": "Praktyki1"
            },
            {
                "time": "11:45-13:15",
                "class_name": "Praktyki (zp)",
                "short_name": "Prakt (zp)",
                "teacher": "PRAKTYKI",
                "room": "Praktyki1"
            },
            {
                "time": "13:30-15:00",
                "class_name": "Praktyki (zp)",
                "short_name": "Prakt (zp)",
                "teacher": "PRAKTYKI",
                "room": "Praktyki1"
            },
            {
                "time": "18:45-20:15",
                "class_name": "Seminarium dyplomowe (sem)",
                "short_name": "Sd (sem)",
                "teacher": "prof. dr hab. inż. Robert Burduk",
                "room": "Online_109"
            }
        ],
        "Środa 2026-03-11": [
            {
                "time": "08:15-09:45",
                "class_name": "Praktyki (zp)",
                "short_name": "Prakt (zp)",
                "teacher": "PRAKTYKI",
                "room": "Praktyki1"
            },
            {
                "time": "10:00-11:30",
                "class_name": "Praktyki (zp)",
                "short_name": "Prakt (zp)",
                "teacher": "PRAKTYKI",
                "room": "Praktyki1"
            },
            {
                "time": "11:45-13:15",
                "class_name": "Praktyki (zp)",
                "short_name": "Prakt (zp)",
                "teacher": "PRAKTYKI",
                "room": "Praktyki1"
            },
            {
                "time": "13:30-15:00",
                "class_name": "Praktyki (zp)",
                "short_name": "Prakt (zp)",
                "teacher": "PRAKTYKI",
                "room": "Praktyki1"
            }
        ],
        "Czwartek 2026-03-12": [
            {
                "time": "08:15-09:45",
                "class_name": "Praktyki (zp)",
                "short_name": "Prakt (zp)",
                "teacher": "PRAKTYKI",
                "room": "Praktyki1"
            },
            {
                "time": "10:00-11:30",
                "class_name": "Praktyki (zp)",
                "short_name": "Prakt (zp)",
                "teacher": "PRAKTYKI",
                "room": "Praktyki1"
            },
            {
                "time": "11:45-13:15",
                "class_name": "Praktyki (zp)",
                "short_name": "Prakt (zp)",
                "teacher": "PRAKTYKI",
                "room": "Praktyki1"
            },
            {
                "time": "13:30-15:00",
                "class_name": "Praktyki (zp)",
                "short_name": "Prakt (zp)",
                "teacher": "PRAKTYKI",
                "room": "Praktyki1"
            }
        ],
        "Piątek 2026-03-13": [
            {
                "time": "08:15-09:45",
                "class_name": "Praktyki (zp)",
                "short_name": "Prakt (zp)",
                "teacher": "PRAKTYKI",
                "room": "Praktyki1"
            },
            {
                "time": "10:00-11:30",
                "class_name": "Praktyki (zp)",
                "short_name": "Prakt (zp)",
                "teacher": "PRAKTYKI",
                "room": "Praktyki1"
            },
            {
                "time": "11:45-13:15",
                "class_name": "Praktyki (zp)",
                "short_name": "Prakt (zp)",
                "teacher": "PRAKTYKI",
                "room": "Praktyki1"
            },
            {
                "time": "13:30-15:00",
                "class_name": "Praktyki (zp)",
                "short_name": "Prakt (zp)",
                "teacher": "PRAKTYKI",
                "room": "Praktyki1"
            },
            {
                "time": "17:00-18:30",
                "class_name": "Seminarium dyplomowe (sem)",
                "short_name": "Sd (sem)",
                "teacher": "prof. dr hab. inż. Anna Burduk / dr inż. Rafał Więcławek",
                "room": "Online_100 / Online_101"
            },
            {
                "time": "18:45-20:15",
                "class_name": "Eksploatacja maszyn i urządzeń (wyk)",
                "short_name": "Emiu (wyk)",
                "teacher": "dr inż. Zygmunt Domagała",
                "room": "Online_09"
            }
        ],
        "Poniedziałek 2026-03-16": [
            {
                "time": "08:15-09:45",
                "class_name": "Praktyki (zp)",
                "short_name": "Prakt (zp)",
                "teacher": "PRAKTYKI",
                "room": "Praktyki1"
            },
            {
                "time": "10:00-11:30",
                "class_name": "Praktyki (zp)",
                "short_name": "Prakt (zp)",
                "teacher": "PRAKTYKI",
                "room": "Praktyki1"
            },
            {
                "time": "11:45-13:15",
                "class_name": "Praktyki (zp)",
                "short_name": "Prakt (zp)",
                "teacher": "PRAKTYKI",
                "room": "Praktyki1"
            },
            {
                "time": "13:30-15:00",
                "class_name": "Praktyki (zp)",
                "short_name": "Prakt (zp)",
                "teacher": "PRAKTYKI",
                "room": "Praktyki1"
            }
        ],
        "Wtorek 2026-03-17": [
            {
                "time": "08:15-09:45",
                "class_name": "Praktyki (zp)",
                "short_name": "Prakt (zp)",
                "teacher": "PRAKTYKI",
                "room": "Praktyki1"
            },
            {
                "time": "10:00-11:30",
                "class_name": "Praktyki (zp)",
                "short_name": "Prakt (zp)",
                "teacher": "PRAKTYKI",
                "room": "Praktyki1"
            },
            {
                "time": "11:45-13:15",
                "class_name": "Praktyki (zp)",
                "short_name": "Prakt (zp)",
                "teacher": "PRAKTYKI",
                "room": "Praktyki1"
            },
            {
                "time": "13:30-15:00",
                "class_name": "Praktyki (zp)",
                "short_name": "Prakt (zp)",
                "teacher": "PRAKTYKI",
                "room": "Praktyki1"
            },
            {
                "time": "18:45-20:15",
                "class_name": "Seminarium dyplomowe (sem)",
                "short_name": "Sd (sem)",
                "teacher": "prof. dr hab. inż. Robert Burduk",
                "room": "Online_08"
            }
        ],
        "Środa 2026-03-18": [
            {
                "time": "08:15-09:45",
                "class_name": "Praktyki (zp)",
                "short_name": "Prakt (zp)",
                "teacher": "PRAKTYKI",
                "room": "Praktyki1"
            },
            {
                "time": "10:00-11:30",
                "class_name": "Praktyki (zp)",
                "short_name": "Prakt (zp)",
                "teacher": "PRAKTYKI",
                "room": "Praktyki1"
            },
            {
                "time": "11:45-13:15",
                "class_name": "Praktyki (zp)",
                "short_name": "Prakt (zp)",
                "teacher": "PRAKTYKI",
                "room": "Praktyki1"
            },
            {
                "time": "13:30-15:00",
                "class_name": "Praktyki (zp)",
                "short_name": "Prakt (zp)",
                "teacher": "PRAKTYKI",
                "room": "Praktyki1"
            }
        ],
        "Czwartek 2026-03-19": [
            {
                "time": "08:15-09:45",
                "class_name": "Praktyki (zp)",
                "short_name": "Prakt (zp)",
                "teacher": "PRAKTYKI",
                "room": "Praktyki1"
            },
            {
                "time": "10:00-11:30",
                "class_name": "Praktyki (zp)",
                "short_name": "Prakt (zp)",
                "teacher": "PRAKTYKI",
                "room": "Praktyki1"
            },
            {
                "time": "11:45-13:15",
                "class_name": "Praktyki (zp)",
                "short_name": "Prakt (zp)",
                "teacher": "PRAKTYKI",
                "room": "Praktyki1"
            },
            {
                "time": "13:30-15:00",
                "class_name": "Praktyki (zp)",
                "short_name": "Prakt (zp)",
                "teacher": "PRAKTYKI",
                "room": "Praktyki1"
            }
        ],
        "Piątek 2026-03-20": [
            {
                "time": "08:15-09:45",
                "class_name": "Praktyki (zp)",
                "short_name": "Prakt (zp)",
                "teacher": "PRAKTYKI",
                "room": "Praktyki1"
            },
            {
                "time": "10:00-11:30",
                "class_name": "Praktyki (zp)",
                "short_name": "Prakt (zp)",
                "teacher": "PRAKTYKI",
                "room": "Praktyki1"
            },
            {
                "time": "11:45-13:15",
                "class_name": "Praktyki (zp)",
                "short_name": "Prakt (zp)",
                "teacher": "PRAKTYKI",
                "room": "Praktyki1"
            },
            {
                "time": "13:30-15:00",
                "class_name": "Praktyki (zp)",
                "short_name": "Prakt (zp)",
                "teacher": "PRAKTYKI",
                "room": "Praktyki1"
            },
            {
                "time": "17:00-18:30",
                "class_name": "Seminarium dyplomowe (sem)",
                "short_name": "Sd (sem)",
                "teacher": "prof. dr hab. inż. Anna Burduk / dr inż. Rafał Więcławek",
                "room": "Online_09 / Online_10"
            },
            {
                "time": "18:45-20:15",
                "class_name": "Eksploatacja maszyn i urządzeń (wyk)",
                "short_name": "Emiu (wyk)",
                "teacher": "dr inż. Zygmunt Domagała",
                "room": "Online_09"
            }
        ],
        "Poniedziałek 2026-03-23": [
            {
                "time": "08:15-09:45",
                "class_name": "Praktyki (zp)",
                "short_name": "Prakt (zp)",
                "teacher": "PRAKTYKI",
                "room": "Praktyki1"
            },
            {
                "time": "10:00-11:30",
                "class_name": "Praktyki (zp)",
                "short_name": "Prakt (zp)",
                "teacher": "PRAKTYKI",
                "room": "Praktyki1"
            },
            {
                "time": "11:45-13:15",
                "class_name": "Praktyki (zp)",
                "short_name": "Prakt (zp)",
                "teacher": "PRAKTYKI",
                "room": "Praktyki1"
            },
            {
                "time": "13:30-15:00",
                "class_name": "Praktyki (zp)",
                "short_name": "Prakt (zp)",
                "teacher": "PRAKTYKI",
                "room": "Praktyki1"
            }
        ],
        "Wtorek 2026-03-24": [
            {
                "time": "08:15-09:45",
                "class_name": "Praktyki (zp)",
                "short_name": "Prakt (zp)",
                "teacher": "PRAKTYKI",
                "room": "Praktyki1"
            },
            {
                "time": "10:00-11:30",
                "class_name": "Praktyki (zp)",
                "short_name": "Prakt (zp)",
                "teacher": "PRAKTYKI",
                "room": "Praktyki1"
            },
            {
                "time": "11:45-13:15",
                "class_name": "Praktyki (zp)",
                "short_name": "Prakt (zp)",
                "teacher": "PRAKTYKI",
                "room": "Praktyki1"
            },
            {
                "time": "13:30-15:00",
                "class_name": "Praktyki (zp)",
                "short_name": "Prakt (zp)",
                "teacher": "PRAKTYKI",
                "room": "Praktyki1"
            },
            {
                "time": "18:45-20:15",
                "class_name": "Seminarium dyplomowe (sem)",
                "short_name": "Sd (sem)",
                "teacher": "prof. dr hab. inż. Robert Burduk",
                "room": "Online_100"
            }
        ],
        "Środa 2026-03-25": [
            {
                "time": "08:15-09:45",
                "class_name": "Praktyki (zp)",
                "short_name": "Prakt (zp)",
                "teacher": "PRAKTYKI",
                "room": "Praktyki1"
            },
            {
                "time": "10:00-11:30",
                "class_name": "Praktyki (zp)",
                "short_name": "Prakt (zp)",
                "teacher": "PRAKTYKI",
                "room": "Praktyki1"
            },
            {
                "time": "11:45-13:15",
                "class_name": "Praktyki (zp)",
                "short_name": "Prakt (zp)",
                "teacher": "PRAKTYKI",
                "room": "Praktyki1"
            },
            {
                "time": "13:30-15:00",
                "class_name": "Praktyki (zp)",
                "short_name": "Prakt (zp)",
                "teacher": "PRAKTYKI",
                "room": "Praktyki1"
            }
        ],
        "Czwartek 2026-03-26": [
            {
                "time": "08:15-09:45",
                "class_name": "Praktyki (zp)",
                "short_name": "Prakt (zp)",
                "teacher": "PRAKTYKI",
                "room": "Praktyki1"
            },
            {
                "time": "10:00-11:30",
                "class_name": "Praktyki (zp)",
                "short_name": "Prakt (zp)",
                "teacher": "PRAKTYKI",
                "room": "Praktyki1"
            },
            {
                "time": "11:45-13:15",
                "class_name": "Praktyki (zp)",
                "short_name": "Prakt (zp)",
                "teacher": "PRAKTYKI",
                "room": "Praktyki1"
            },
            {
                "time": "13:30-15:00",
                "class_name": "Praktyki (zp)",
                "short_name": "Prakt (zp)",
                "teacher": "PRAKTYKI",
                "room": "Praktyki1"
            },
            {
                "time": "18:45-20:15",
                "class_name": "Zintegrowane systemy informatyczne zarządzania (wyk)",
                "short_name": "Zsiz (wyk)",
                "teacher": "mgr inż. Dawid Kucuk",
                "room": "Online_01"
            }
        ],
        "Piątek 2026-03-27": [
            {
                "time": "08:15-09:45",
                "class_name": "Praktyki (zp)",
                "short_name": "Prakt (zp)",
                "teacher": "PRAKTYKI",
                "room": "Praktyki1"
            },
            {
                "time": "10:00-11:30",
                "class_name": "Praktyki (zp)",
                "short_name": "Prakt (zp)",
                "teacher": "PRAKTYKI",
                "room": "Praktyki1"
            },
            {
                "time": "11:45-13:15",
                "class_name": "Praktyki (zp)",
                "short_name": "Prakt (zp)",
                "teacher": "PRAKTYKI",
                "room": "Praktyki1"
            },
            {
                "time": "13:30-15:00",
                "class_name": "Praktyki (zp)",
                "short_name": "Prakt (zp)",
                "teacher": "PRAKTYKI",
                "room": "Praktyki1"
            },
            {
                "time": "18:45-20:15",
                "class_name": "Seminarium dyplomowe (sem)",
                "short_name": "Sd (sem)",
                "teacher": "prof. dr hab. inż. Anna Burduk",
                "room": "Online_08"
            }
        ],
        "Wtorek 2026-03-31": [
            {
                "time": "18:45-20:15",
                "class_name": "Seminarium dyplomowe (sem)",
                "short_name": "Sd (sem)",
                "teacher": "prof. dr hab. inż. Robert Burduk",
                "room": "Online_10"
            }
        ],
        "Wtorek 2026-04-07": [
            {
                "time": "18:45-20:15",
                "class_name": "Seminarium dyplomowe (sem)",
                "short_name": "Sd (sem)",
                "teacher": "prof. dr hab. inż. Robert Burduk",
                "room": "Online_01"
            }
        ],
        "Czwartek 2026-04-09": [
            {
                "time": "18:45-20:15",
                "class_name": "Zintegrowane systemy informatyczne zarządzania (wyk)",
                "short_name": "Zsiz (wyk)",
                "teacher": "mgr inż. Dawid Kucuk",
                "room": "Online_04"
            }
        ],
        "Piątek 2026-04-10": [
            {
                "time": "17:00-18:30",
                "class_name": "Seminarium dyplomowe (sem)",
                "short_name": "Sd (sem)",
                "teacher": "dr inż. Rafał Więcławek / prof. dr hab. inż. Anna Burduk",
                "room": "Online_08 / Online_105"
            },
            {
                "time": "18:45-20:15",
                "class_name": "Eksploatacja maszyn i urządzeń (wyk)",
                "short_name": "Emiu (wyk)",
                "teacher": "dr inż. Zygmunt Domagała",
                "room": "Online_07"
            }
        ],
        "Sobota 2026-04-11": [
            {
                "time": "11:45-13:15",
                "class_name": "Zintegrowane systemy informatyczne zarządzania (lab)",
                "short_name": "Zsiz (lab)",
                "teacher": "mgr inż. Dawid Kucuk",
                "room": "C313"
            },
            {
                "time": "13:45-15:15",
                "class_name": "Zintegrowane systemy informatyczne zarządzania (lab)",
                "short_name": "Zsiz (lab)",
                "teacher": "mgr inż. Dawid Kucuk",
                "room": "C313"
            },
            {
                "time": "15:30-17:00",
                "class_name": "Eksploatacja maszyn i urządzeń (wt)",
                "short_name": "Emiu (wt)",
                "teacher": "dr inż. Zygmunt Domagała",
                "room": "C326"
            },
            {
                "time": "17:15-18:45",
                "class_name": "Eksploatacja maszyn i urządzeń (wt)",
                "short_name": "Emiu (wt)",
                "teacher": "dr inż. Zygmunt Domagała",
                "room": "C326"
            },
            {
                "time": "19:00-20:30",
                "class_name": "Eksploatacja maszyn i urządzeń (wt)",
                "short_name": "Emiu (wt)",
                "teacher": "dr inż. Zygmunt Domagała",
                "room": "C326"
            }
        ],
        "Wtorek 2026-04-14": [
            {
                "time": "18:45-20:15",
                "class_name": "Seminarium dyplomowe (sem)",
                "short_name": "Sd (sem)",
                "teacher": "prof. dr hab. inż. Robert Burduk",
                "room": "Online_105"
            }
        ],
        "Piątek 2026-04-17": [
            {
                "time": "17:00-18:30",
                "class_name": "Seminarium dyplomowe (sem)",
                "short_name": "Sd (sem)",
                "teacher": "prof. dr hab. inż. Anna Burduk / dr inż. Rafał Więcławek",
                "room": "Online_10 / Online_100"
            },
            {
                "time": "18:45-20:15",
                "class_name": "Seminarium dyplomowe (sem)",
                "short_name": "Sd (sem)",
                "teacher": "prof. dr hab. inż. Anna Burduk / dr inż. Rafał Więcławek",
                "room": "Online_10 / Online_100"
            }
        ],
        "Sobota 2026-04-18": [
            {
                "time": "15:30-17:00",
                "class_name": "BAL WITELONA (wt)",
                "short_name": "BW (wt)",
                "teacher": "BAL WITELONA",
                "room": "Inne_Bal Witelona"
            },
            {
                "time": "17:15-18:45",
                "class_name": "BAL WITELONA (wt)",
                "short_name": "BW (wt)",
                "teacher": "BAL WITELONA",
                "room": "Inne_Bal Witelona"
            },
            {
                "time": "19:00-20:30",
                "class_name": "BAL WITELONA (wt)",
                "short_name": "BW (wt)",
                "teacher": "BAL WITELONA",
                "room": "Inne_Bal Witelona"
            }
        ],
        "Niedziela 2026-04-19": [
            {
                "time": "08:15-09:45",
                "class_name": "BAL WITELONA (wt)",
                "short_name": "BW (wt)",
                "teacher": "BAL WITELONA",
                "room": "Inne_Bal Witelona"
            },
            {
                "time": "10:00-11:30",
                "class_name": "BAL WITELONA (wt)",
                "short_name": "BW (wt)",
                "teacher": "BAL WITELONA",
                "room": "Inne_Bal Witelona"
            }
        ],
        "Czwartek 2026-04-23": [
            {
                "time": "18:45-20:15",
                "class_name": "Zintegrowane systemy informatyczne zarządzania (wyk)",
                "short_name": "Zsiz (wyk)",
                "teacher": "mgr inż. Dawid Kucuk",
                "room": "Online_05"
            }
        ],
        "Piątek 2026-04-24": [
            {
                "time": "17:00-18:30",
                "class_name": "Seminarium dyplomowe (sem)",
                "short_name": "Sd (sem)",
                "teacher": "prof. dr hab. inż. Anna Burduk / dr inż. Rafał Więcławek",
                "room": "Online_100 / Online_102"
            },
            {
                "time": "18:45-20:15",
                "class_name": "Eksploatacja maszyn i urządzeń (wyk)",
                "short_name": "Emiu (wyk)",
                "teacher": "dr inż. Zygmunt Domagała",
                "room": "Online_100"
            }
        ],
        "Sobota 2026-04-25": [
            {
                "time": "19:00-20:30",
                "class_name": "Rola współczesnego menedżera w przemyśle 4.0 (wt)",
                "short_name": "Rwmwp4 (wt)",
                "teacher": "mgr inż. Piotr Motyka",
                "room": "C202"
            }
        ],
        "Wtorek 2026-04-28": [
            {
                "time": "15:15-16:45",
                "class_name": "Seminarium dyplomowe (sem)",
                "short_name": "Sd (sem)",
                "teacher": "prof. dr hab. inż. Robert Burduk",
                "room": "Online_109"
            },
            {
                "time": "17:00-18:30",
                "class_name": "Seminarium dyplomowe (sem)",
                "short_name": "Sd (sem)",
                "teacher": "prof. dr hab. inż. Robert Burduk",
                "room": "Online_109"
            }
        ],
        "Wtorek 2026-05-05": [
            {
                "time": "18:45-20:15",
                "class_name": "Seminarium dyplomowe (sem)",
                "short_name": "Sd (sem)",
                "teacher": "prof. dr hab. inż. Robert Burduk",
                "room": "Online_102"
            }
        ],
        "Czwartek 2026-05-07": [
            {
                "time": "18:45-20:15",
                "class_name": "Zintegrowane systemy informatyczne zarządzania (wyk)",
                "short_name": "Zsiz (wyk)",
                "teacher": "mgr inż. Dawid Kucuk",
                "room": "Online_03"
            }
        ],
        "Piątek 2026-05-08": [
            {
                "time": "15:15-16:45",
                "class_name": "Seminarium dyplomowe (sem)",
                "short_name": "Sd (sem)",
                "teacher": "dr inż. Rafał Więcławek",
                "room": "Online_07"
            },
            {
                "time": "17:00-18:30",
                "class_name": "Seminarium dyplomowe (sem)",
                "short_name": "Sd (sem)",
                "teacher": "dr inż. Rafał Więcławek / prof. dr hab. inż. Anna Burduk",
                "room": "Online_07 / Online_08"
            },
            {
                "time": "18:45-20:15",
                "class_name": "Seminarium dyplomowe (sem)",
                "short_name": "Sd (sem)",
                "teacher": "prof. dr hab. inż. Robert Burduk",
                "room": "Online_07"
            }
        ],
        "Wtorek 2026-05-12": [
            {
                "time": "18:45-20:15",
                "class_name": "Seminarium dyplomowe (sem)",
                "short_name": "Sd (sem)",
                "teacher": "prof. dr hab. inż. Robert Burduk",
                "room": "Online_07"
            }
        ],
        "Środa 2026-05-13": [
            {
                "time": "17:00-18:30",
                "class_name": "Zintegrowane systemy informatyczne zarządzania (wyk)",
                "short_name": "Zsiz (wyk)",
                "teacher": "mgr inż. Dawid Kucuk",
                "room": "A245"
            },
            {
                "time": "18:45-20:15",
                "class_name": "Eksploatacja maszyn i urządzeń (wyk)",
                "short_name": "Emiu (wyk)",
                "teacher": "dr inż. Zygmunt Domagała",
                "room": "A245"
            }
        ],
        "Piątek 2026-05-15": [
            {
                "time": "17:00-18:30",
                "class_name": "Seminarium dyplomowe (sem)",
                "short_name": "Sd (sem)",
                "teacher": "dr inż. Rafał Więcławek / prof. dr hab. inż. Anna Burduk",
                "room": "Online_08 / Online_09"
            },
            {
                "time": "18:45-20:15",
                "class_name": "Seminarium dyplomowe (sem)",
                "short_name": "Sd (sem)",
                "teacher": "prof. dr hab. inż. Anna Burduk / dr inż. Rafał Więcławek",
                "room": "Online_09 / Online_101"
            }
        ],
        "Sobota 2026-05-16": [
            {
                "time": "11:45-13:15",
                "class_name": "Zintegrowane systemy informatyczne zarządzania (lab)",
                "short_name": "Zsiz (lab)",
                "teacher": "mgr inż. Dawid Kucuk",
                "room": "A244"
            },
            {
                "time": "13:45-15:15",
                "class_name": "Seminarium dyplomowe (sem)",
                "short_name": "Sd (sem)",
                "teacher": "prof. dr hab. inż. Anna Burduk / prof. dr hab. inż. Robert Burduk / dr inż. Rafał Więcławek",
                "room": "A142 / C202 / C227"
            },
            {
                "time": "15:30-17:00",
                "class_name": "Seminarium dyplomowe (sem)",
                "short_name": "Sd (sem)",
                "teacher": "prof. dr hab. inż. Anna Burduk / prof. dr hab. inż. Robert Burduk / dr inż. Rafał Więcławek",
                "room": "A142 / C202 / C227"
            },
            {
                "time": "17:15-18:45",
                "class_name": "Coboty w przemyśle (lab)",
                "short_name": "Cwp (lab)",
                "teacher": "mgr inż. Jakub Wisłocki",
                "room": "D6"
            }
        ],
        "Niedziela 2026-05-17": [
            {
                "time": "08:15-09:45",
                "class_name": "Coboty w przemyśle (lab)",
                "short_name": "Cwp (lab)",
                "teacher": "mgr inż. Jakub Wisłocki",
                "room": "D6"
            },
            {
                "time": "10:00-11:30",
                "class_name": "Coboty w przemyśle (lab)",
                "short_name": "Cwp (lab)",
                "teacher": "mgr inż. Jakub Wisłocki",
                "room": "D6"
            },
            {
                "time": "11:45-13:15",
                "class_name": "Eksploatacja maszyn i urządzeń (wt)",
                "short_name": "Emiu (wt)",
                "teacher": "dr inż. Zygmunt Domagała",
                "room": "C329"
            },
            {
                "time": "13:45-15:15",
                "class_name": "Eksploatacja maszyn i urządzeń (wt)",
                "short_name": "Emiu (wt)",
                "teacher": "dr inż. Zygmunt Domagała",
                "room": "C329"
            },
            {
                "time": "15:30-17:00",
                "class_name": "Coboty w przemyśle (lab)",
                "short_name": "Cwp (lab)",
                "teacher": "mgr inż. Jakub Wisłocki",
                "room": "D6"
            },
            {
                "time": "17:15-18:45",
                "class_name": "Rola współczesnego menedżera w przemyśle 4.0 (wt)",
                "short_name": "Rwmwp4 (wt)",
                "teacher": "mgr inż. Piotr Motyka",
                "room": "C202"
            },
            {
                "time": "19:00-20:30",
                "class_name": "Zintegrowane systemy informatyczne zarządzania (lab)",
                "short_name": "Zsiz (lab)",
                "teacher": "mgr inż. Dawid Kucuk",
                "room": "A244"
            }
        ]
    }
}